DKCloudCommand/__init__.py
DKCloudCommand/logging_cfg.py
DKCloudCommand/version.py
DKCloudCommand/cli/__init__.py
DKCloudCommand/cli/__main__.py
DKCloudCommand/hooks/DKHooks.py
DKCloudCommand/hooks/__init__.py
DKCloudCommand/modules/DKActiveServingWatcher.py
DKCloudCommand/modules/DKCCUserTracking.py
DKCloudCommand/modules/DKCLIRecipeChecker.py
DKCloudCommand/modules/DKCloudAPI.py
DKCloudCommand/modules/DKCloudCommandConfig.py
DKCloudCommand/modules/DKCloudCommandRunner.py
DKCloudCommand/modules/DKDateHelper.py
DKCloudCommand/modules/DKFileHelper.py
DKCloudCommand/modules/DKIgnore.py
DKCloudCommand/modules/DKKitchenDisk.py
DKCloudCommand/modules/DKRecipeDisk.py
DKCloudCommand/modules/DKReturnCode.py
DKCloudCommand/modules/DKZipHelper.py
DKCloudCommand/modules/__init__.py
DKCloudCommand/modules/githash.py
DKCommon/Constants.py
DKCommon/DKFileEncode.py
DKCommon/DKJSONUtils.py
DKCommon/DKMongoUtils.py
DKCommon/DKPathUtils.py
DKCommon/DKUserTracking.py
DKCommon/Exceptions.py
DKCommon/OAuthConstants.py
DKCommon/RequestInfo.py
DKCommon/__init__.py
DKCommon/dt_utils.py
DKCommon/log_utils.py
DKCommon/str_utils.py
DKCommon/typing.py
DKCommon/api_utils/DKApiHelper.py
DKCommon/api_utils/DKErrors.py
DKCommon/api_utils/DKReturnCode.py
DKCommon/api_utils/__init__.py
DKCommon/api_utils/api_utils.py
DKCommon/constants/__init__.py
DKCommon/constants/authentication.py
DKCommon/constants/entities.py
DKCommon/constants/api/__init__.py
DKCommon/constants/api/environment.py
DKCommon/constants/api/errors.py
DKCommon/constants/api/query_params.py
DKCommon/email_templates/DKKitchenMergeTemplate.py
DKCommon/email_templates/DKPasswordResetTemplate.py
DKCommon/email_templates/DKUserInviteTemplate.py
DKCommon/email_templates/__init__.py
DKCommon/jsonparse/JSONLexer.py
DKCommon/jsonparse/JSONListener.py
DKCommon/jsonparse/JSONParser.py
DKCommon/jsonparse/__init__.py
DKCommon/request_extensions/__init__.py
DKCommon/request_extensions/auth_adapter.py
DKCommon/request_extensions/hooks.py
DKCloudCommand-1.4.1.dist-info/LICENSE
DKCloudCommand-1.4.1.dist-info/LICENSE.txt
DKCloudCommand-1.4.1.dist-info/METADATA
DKCloudCommand-1.4.1.dist-info/WHEEL
DKCloudCommand-1.4.1.dist-info/entry_points.txt
DKCloudCommand-1.4.1.dist-info/top_level.txt
DKCloudCommand-1.4.1.dist-info/RECORD
