Metadata-Version: 2.1
Name: DKCloudCommand
Version: 1.4.1
Summary: DataKitchen Cloud Command Line
Author: DataKitchen
Author-email: info@datakitchen.io
Keywords: DataKitchen,Cloud,Commandline,Analytics,Agile Data,DataOps
Requires-Python: >=3.6
License-File: LICENSE
License-File: LICENSE.txt
Requires-Dist: aniso8601 ==9.0.1
Requires-Dist: boltons ==23.0.0
Requires-Dist: click ==8.0.4
Requires-Dist: Jinja2 ==3.0.3
Requires-Dist: chardet >=5.0.0
Requires-Dist: mixpanel ==4.10.0
Requires-Dist: prettytable ==2.5.0
Requires-Dist: PyJWT ==2.4.0
Requires-Dist: pyOpenSSL ==23.1.1
Requires-Dist: pytz ==2023.3
Requires-Dist: requests ==2.29.0
Requires-Dist: urllib3 ==1.26.15
Requires-Dist: websocket-client ==1.3.1
Requires-Dist: idna ==2.6
Requires-Dist: importlib-metadata ==4.8.3
Requires-Dist: MarkupSafe ==2.0.1
Requires-Dist: typing-extensions ==4.1.1
Requires-Dist: wcwidth ==0.2.6
Requires-Dist: zipp ==3.6.0
